README.md
setup.py
colabo/__init__.py
colabo.flow.go.egg-info/PKG-INFO
colabo.flow.go.egg-info/SOURCES.txt
colabo.flow.go.egg-info/dependency_links.txt
colabo.flow.go.egg-info/requires.txt
colabo.flow.go.egg-info/top_level.txt
colabo/flow/__init__.py
colabo/flow/go/__init__.py
colabo/flow/go/colaboflow_go_actionhost.py
colabo/flow/go/colaboflow_go_client.py
colabo/flow/go/colaboflow_go_demo.py
colabo/flow/go/go_pb2.py
colabo/flow/go/go_pb2_grpc.py
use-cases/__init__.py