Metadata-Version: 2.1
Name: colabo.flow.go
Version: 0.2.2
Summary: A python puzzle for sending ColaboFlow.Go (CF.Go) actions over gRPC
Home-page: https://github.com/Cha-OS/colabo
Author: ChaOS
Author-email: chaos.ngo@gmail.com
License: MIT
Project-URL: website, http://colabo.space
Project-URL: organization, http://cha-os.org
Keywords: colabo,grpc,flow,colaboflow,go,process,process mining
Platform: UNKNOWN
